gmx_top4py/__init__.py
gmx_top4py/constants.py
gmx_top4py/parameterizing.py
gmx_top4py/parsing.py
gmx_top4py/utils.py
gmx_top4py/__pycache__/__init__.cpython-310.pyc
gmx_top4py/__pycache__/__init__.cpython-311.pyc
gmx_top4py/__pycache__/__init__.cpython-312.pyc
gmx_top4py/__pycache__/__init__.cpython-313.pyc
gmx_top4py/__pycache__/__init__.cpython-314.pyc
gmx_top4py/__pycache__/constants.cpython-310.pyc
gmx_top4py/__pycache__/constants.cpython-311.pyc
gmx_top4py/__pycache__/constants.cpython-312.pyc
gmx_top4py/__pycache__/constants.cpython-313.pyc
gmx_top4py/__pycache__/constants.cpython-314.pyc
gmx_top4py/__pycache__/parameterizing.cpython-310.pyc
gmx_top4py/__pycache__/parameterizing.cpython-311.pyc
gmx_top4py/__pycache__/parameterizing.cpython-312.pyc
gmx_top4py/__pycache__/parameterizing.cpython-313.pyc
gmx_top4py/__pycache__/parameterizing.cpython-314.pyc
gmx_top4py/__pycache__/parsing.cpython-310.pyc
gmx_top4py/__pycache__/parsing.cpython-311.pyc
gmx_top4py/__pycache__/parsing.cpython-312.pyc
gmx_top4py/__pycache__/parsing.cpython-313.pyc
gmx_top4py/__pycache__/parsing.cpython-314.pyc
gmx_top4py/__pycache__/utils.cpython-310.pyc
gmx_top4py/__pycache__/utils.cpython-311.pyc
gmx_top4py/__pycache__/utils.cpython-312.pyc
gmx_top4py/__pycache__/utils.cpython-313.pyc
gmx_top4py/__pycache__/utils.cpython-314.pyc
gmx_top4py/topology/atomic.py
gmx_top4py/topology/ff.py
gmx_top4py/topology/topology.py
gmx_top4py/topology/utils.py
gmx_top4py/topology/__pycache__/atomic.cpython-310.pyc
gmx_top4py/topology/__pycache__/atomic.cpython-311.pyc
gmx_top4py/topology/__pycache__/atomic.cpython-312.pyc
gmx_top4py/topology/__pycache__/atomic.cpython-313.pyc
gmx_top4py/topology/__pycache__/atomic.cpython-314.pyc
gmx_top4py/topology/__pycache__/ff.cpython-310.pyc
gmx_top4py/topology/__pycache__/ff.cpython-311.pyc
gmx_top4py/topology/__pycache__/ff.cpython-312.pyc
gmx_top4py/topology/__pycache__/ff.cpython-313.pyc
gmx_top4py/topology/__pycache__/ff.cpython-314.pyc
gmx_top4py-0.1.5.dist-info/licenses/LICENSE
gmx_top4py-0.1.5.dist-info/METADATA
gmx_top4py-0.1.5.dist-info/WHEEL
gmx_top4py-0.1.5.dist-info/top_level.txt
gmx_top4py-0.1.5.dist-info/RECORD
